pybitflyer2/__init__.py
pybitflyer2/connection.py
pybitflyer2/http_private.py
pybitflyer2/http_public.py
pybitflyer2/realtimeclient.py
pybitflyer2-0.0.3.dist-info/LICENSE
pybitflyer2-0.0.3.dist-info/WHEEL
pybitflyer2-0.0.3.dist-info/METADATA
pybitflyer2-0.0.3.dist-info/RECORD
