Metadata-Version: 2.1
Name: pybitflyer2
Version: 0.0.3
Summary: pybitflyer2 is a wrapper interface of Bitflyer lightning API
Home-page: https://github.com/fkshom/pybitflyer2
License: MIT
Author: Shoma FUKUDA
Author-email: fkshom+pypi@gmail.com
Requires-Python: >=3.6,<4.0
Classifier: Development Status :: 3 - Alpha
Classifier: Environment :: Console
Classifier: Intended Audience :: Developers
Classifier: License :: OSI Approved :: MIT License
Classifier: Programming Language :: Python :: 3
Classifier: Programming Language :: Python :: 3.6
Classifier: Programming Language :: Python :: 3.7
Classifier: Programming Language :: Python :: 3.8
Classifier: Programming Language :: Python :: 3.9
Classifier: Topic :: Utilities
Requires-Dist: requests (>=2.26.0,<3.0.0)
Requires-Dist: websocket-client (>=1.2.0,<2.0.0)
Project-URL: Documentation, https://github.com/fkshom/pybitflyer2
Project-URL: Repository, https://github.com/fkshom/pybitflyer2
